[{"description":"","id":"profile privacy","keyword":"Feature","line":1,"name":"Profile Privacy","uri":"C:\\Users\\franc\\Desktop\\rateIT\\app\\test_driver\\features\\profilePrivacy.feature","elements":[{"keyword":"Scenario","type":"scenario","id":"profile privacy;user sets their profile to private","name":"User sets their profile to private","description":"","line":4,"steps":[{"keyword":"Given ","name":"the user has an account on the app","line":5,"match":{"location":"C:\\Users\\franc\\Desktop\\rateIT\\app\\test_driver\\features\\profilePrivacy.feature:5"},"result":{"status":"failed","duration":0,"error_message":"GherkinStepNotDefinedException:       Step definition not found for text:\n\n        'Given the user has an account on the app'\n\n      File path: C:\\Users\\franc\\Desktop\\rateIT\\app\\test_driver\\features\\profilePrivacy.feature#4\n      Line:      Given the user has an account on the app\n\n      ---------------------------------------------\n\n      You must implement the step like below and add the class to the 'stepDefinitions' property in your configuration:\n\n      /// The 'Given' class prefix can be replaced with 'Then', 'When' 'And' or 'But'\n      /// All classes can take up to 5 input parameters. With more, you should probably use a table.\n      /// For example: `When4<String, bool, int, num>`\n      /// You can also specify the type of world context you want\n      /// `When4WithWorld<String, bool, int, num, MyWorld>`\n      class Given_Given_the_user_has_an_account_on_the_app extends Given1<String> {\n        @override\n        RegExp get pattern => RegExp(r\"the user has an account on the app\");\n\n        @override\n        Future<void> executeStep(String input1) async {\n          // If the step is \"Given I do a 'windy pop'\"\n          // in this example, input1 would equal 'windy pop'\n\n          // your code...\n        }\n      }\n      \n\n#0      FeatureFileRunner._matchStepToExecutableStep (package:gherkin/src/feature_file_runner.dart:413:7)\n#1      FeatureFileRunner._runStep (package:gherkin/src/feature_file_runner.dart:332:20)\n<asynchronous suspension>\n#2      FeatureFileRunner._runScenario (package:gherkin/src/feature_file_runner.dart:256:24)\n<asynchronous suspension>\n#3      FeatureFileRunner._runScenarioInZone.<anonymous closure> (package:gherkin/src/feature_file_runner.dart:149:24)\n<asynchronous suspension>"}}]}]}]